AUTHORS.rst
CONTRIBUTING.rst
HISTORY.rst
LICENSE
MANIFEST.in
README.rst
setup.cfg
setup.py
chackpasspy/__init__.py
chackpasspy/chackpasspy.py
chackpasspy/cli.py
chackpasspy.egg-info/PKG-INFO
chackpasspy.egg-info/SOURCES.txt
chackpasspy.egg-info/dependency_links.txt
chackpasspy.egg-info/entry_points.txt
chackpasspy.egg-info/not-zip-safe
chackpasspy.egg-info/requires.txt
chackpasspy.egg-info/top_level.txt
docs/Makefile
docs/authors.rst
docs/chackpasspy.rst
docs/conf.py
docs/contributing.rst
docs/history.rst
docs/index.rst
docs/installation.rst
docs/make.bat
docs/modules.rst
docs/readme.rst
docs/usage.rst
docs/_build/html/_static/ajax-loader.gif
docs/_build/html/_static/comment-bright.png
docs/_build/html/_static/comment-close.png
docs/_build/html/_static/comment.png
docs/_build/html/_static/down-pressed.png
docs/_build/html/_static/down.png
docs/_build/html/_static/file.png
docs/_build/html/_static/minus.png
docs/_build/html/_static/plus.png
docs/_build/html/_static/up-pressed.png
docs/_build/html/_static/up.png
tests/test_chackpasspy.py