Metadata-Version: 1.1
Name: chackpasspy
Version: 0.6.0
Summary: Verifica si el string que se le pasa a la funcion puede ser considerada como una contraseña segura.
Home-page: https://github.com/DaielChom/chackpasspy
Author: DaielChom
Author-email: danielcarvajalpatino@gmail.com
License: MIT license
Keywords: chackpasspy
Platform: UNKNOWN
Classifier: Development Status :: 2 - Pre-Alpha
Classifier: Intended Audience :: Developers
Classifier: License :: OSI Approved :: MIT License
Classifier: Natural Language :: English
Classifier: Programming Language :: Python :: 2
Classifier: Programming Language :: Python :: 2.7
Classifier: Programming Language :: Python :: 3
Classifier: Programming Language :: Python :: 3.4
Classifier: Programming Language :: Python :: 3.5
Classifier: Programming Language :: Python :: 3.6
